pyhwpx/FilePathCheckerModule.dll
pyhwpx/__init__.py
pyhwpx/core.py
pyhwpx/fonts.json
pyhwpx/fonts.py
pyhwpx/param_helpers.py
pyhwpx/run_methods.py
pyhwpx/version.py
pyhwpx/__pycache__/__init__.cpython-312.pyc
pyhwpx/__pycache__/core.cpython-312.pyc
pyhwpx/__pycache__/fonts.cpython-312.pyc
pyhwpx/__pycache__/param_helpers.cpython-312.pyc
pyhwpx/__pycache__/run_methods.cpython-312.pyc
pyhwpx/__pycache__/version.cpython-312.pyc
pyhwpx-1.6.6.dist-info/licenses/license.txt
pyhwpx-1.6.6.dist-info/METADATA
pyhwpx-1.6.6.dist-info/WHEEL
pyhwpx-1.6.6.dist-info/top_level.txt
pyhwpx-1.6.6.dist-info/RECORD
