Metadata-Version: 2.4
Name: pyhwpx
Version: 1.6.6
Summary: 아래아한글 자동화를 위한 파이썬 모듈 pyhwpx입니다.
Home-page: https://martiniifun.github.io/pyhwpx/
Author: ilco
Author-email: martinii.fun@gmail.com
Classifier: Operating System :: Microsoft :: Windows
Requires-Python: >= 3.9
License-File: license.txt
Requires-Dist: numpy
Requires-Dist: pandas
Requires-Dist: pywin32
Requires-Dist: openpyxl
Requires-Dist: pyperclip
Requires-Dist: Pillow
Dynamic: author
Dynamic: author-email
Dynamic: classifier
Dynamic: description
Dynamic: description-content-type
Dynamic: home-page
Dynamic: license-file
Dynamic: requires-dist
Dynamic: requires-python
Dynamic: summary
